AUTHORS
CHANGELOG
CONTRIBUTING.rst
INSTALL
LICENSE
MANIFEST.in
README.rst
VERSION
setup.cfg
setup.py
django_json_dbindex.egg-info/PKG-INFO
django_json_dbindex.egg-info/SOURCES.txt
django_json_dbindex.egg-info/dependency_links.txt
django_json_dbindex.egg-info/not-zip-safe
django_json_dbindex.egg-info/pbr.json
django_json_dbindex.egg-info/requires.txt
django_json_dbindex.egg-info/top_level.txt
json_dbindex/__init__.py
json_dbindex/models.py
json_dbindex/pgcommands.py
json_dbindex/pgcommands.py~
json_dbindex/tests.py
json_dbindex/tests_pg.py
json_dbindex/tests_pg.py~
json_dbindex/util.py
json_dbindex/management/__init__.py
json_dbindex/management/commands/__init__.py
json_dbindex/management/commands/check_jsdbindex.py
json_dbindex/management/commands/create_jsdbindex.py
json_dbindex/management/commands/drop_jsdbindex.py
json_dbindex/management/commands/list_jsdbindex.py
json_dbindex/samples/dbindex_create.json
json_dbindex/samples/dbindex_create.json~
json_dbindex/samples/dbindex_create2.json
json_dbindex/samples/dbindex_create2.json~
json_dbindex/samples/dbindex_drop.json
json_dbindex/samples/dbindex_drop.json~