Metadata-Version: 1.1
Name: django-json-dbindex
Version: 1.2.3
Summary: Django complementary index definition and management.
Home-page: https://django-json-dbindex.readthedocs.org/
Author: Rodolphe Quiédeville
Author-email: rodolphe@quiedeville.org
License: BSD
Keywords: json-dbindex database index postgresql django
Platform: UNKNOWN
Classifier: Programming Language :: Python :: 2.7
Classifier: Development Status :: 5 - Production/Stable
Classifier: Framework :: Django
Classifier: License :: OSI Approved :: BSD License
